rnx/__init__.py
rnx/rnx.py
rnx/test.py
rnx/Kyle Leland version/rnx_3.py
rnx/Kyle Leland version/rnx_3_test.py
rnx-1.1.3.dist-info/LICENSE.txt
rnx-1.1.3.dist-info/METADATA
rnx-1.1.3.dist-info/WHEEL
rnx-1.1.3.dist-info/top_level.txt
rnx-1.1.3.dist-info/RECORD
