Metadata-Version: 2.1
Name: rnx
Version: 1.1.3
Summary: A library to read RINEX files
Author-email: David Woodburn <david.woodburn@icloud.com>
License: MIT
Project-URL: Homepage, https://gitlab.com/davidwoodburn/rnx
Project-URL: Bug Tracker, https://gitlab.com/davidwoodburn/rnx/-/issues
Classifier: Programming Language :: Python :: 3
Classifier: License :: OSI Approved :: MIT License
Classifier: Operating System :: OS Independent
Requires-Python: >=3.6
License-File: LICENSE.txt
Requires-Dist: numpy
